k3logcollector/__init__.py
k3logcollector/cache_flusher.py
k3logcollector/collector.py
k3logcollector/scanner.py
k3logcollector/sender.py
k3logcollector/synopsis.py
k3logcollector-0.1.4.dist-info/licenses/LICENSE
k3logcollector-0.1.4.dist-info/METADATA
k3logcollector-0.1.4.dist-info/WHEEL
k3logcollector-0.1.4.dist-info/top_level.txt
k3logcollector-0.1.4.dist-info/RECORD
